Metadata-Version: 2.1
Name: TheArtist
Version: 1.0.0
Summary: Plotting class preferences of guemesturb
Home-page: https://github.com/guemesturb/TheArtist
Author: Alejandro G"uemes
Author-email: guemes.turb@gmail.com
License: MIT
Platform: UNKNOWN
